Workbook

Sheet Asset_Data
A1: Asset ID | B1: Asset Name | C1: Media Type | D1: Category | E1: Production Date | F1: Equipment Cost | G1: Labor Cost | H1: Software Cost | I1: Post-Production Cost | J1: Revenue Generated | K1: Hours Spent | L1: Total Cost | M1: Profit | N1: ROI %
A2: 1 | B2: Cinematic_Asset_046 | C2: Cinematic Animation Video | D2: Video | E2: 2025-02-22 | F2: 1145 | G2: 14771 | H2: 2141 | I2: 8242 | J2: 64013 | K2: 510 | L2: =F2+G2+H2+I2 -> 26299 | M2: =J2-L2 -> 37714 | N2: =ROUND((J2-L2)/L2*100,2) -> 143.4
A3: 2 | B3: Cinematic_Asset_026 | C3: Cinematic Animation Video | D3: Video | E3: 2025-08-11 | F3: 1496 | G3: 8155 | H3: 988 | I3: 5966 | J3: 19311 | K3: 213.8 | L3: =F3+G3+H3+I3 -> 16605 | M3: =J3-L3 -> 2706 | N3: =ROUND((J3-L3)/L3*100,2) -> 16.3
A4: 3 | B4: Short_Asset_090 | C4: Short Reel | D4: Video | E4: 2025-11-25 | F4: 302 | G4: 2306 | H4: 427 | I4: 656 | J4: 10107 | K4: 52.3 | L4: =F4+G4+H4+I4 -> 3691 | M4: =J4-L4 -> 6416 | N4: =ROUND((J4-L4)/L4*100,2) -> 173.83
A5: 4 | B5: DSLR_Asset_017 | C5: DSLR Portrait | D5: Photography | E5: 2025-11-08 | F5: 1590 | G5: 1800 | H5: 138 | I5: 592 | J5: 7316 | K5: 71.1 | L5: =F5+G5+H5+I5 -> 4120 | M5: =J5-L5 -> 3196 | N5: =ROUND((J5-L5)/L5*100,2) -> 77.57
A6: 5 | B6: Product_Asset_052 | C6: Product Photo | D6: Photography | E6: 2025-06-09 | F6: 648 | G6: 1599 | H6: 102 | I6: 617 | J6: 7772 | K6: 37 | L6: =F6+G6+H6+I6 -> 2966 | M6: =J6-L6 -> 4806 | N6: =ROUND((J6-L6)/L6*100,2) -> 162.04
A7: 6 | B7: Product_Asset_061 | C7: Product Photo | D7: Photography | E7: 2025-03-03 | F7: 957 | G7: 1952 | H7: 111 | I7: 802 | J7: 6792 | K7: 44.8 | L7: =F7+G7+H7+I7 -> 3822 | M7: =J7-L7 -> 2970 | N7: =ROUND((J7-L7)/L7*100,2) -> 77.71
A8: 7 | B8: DSLR_Asset_005 | C8: DSLR Portrait | D8: Photography | E8: 2025-04-17 | F8: 2393 | G8: 3400 | H8: 267 | I8: 951 | J8: 17273 | K8: 114.6 | L8: =F8+G8+H8+I8 -> 7011 | M8: =J8-L8 -> 10262 | N8: =ROUND((J8-L8)/L8*100,2) -> 146.37
A9: 8 | B9: Cinematic_Asset_039 | C9: Cinematic Animation Video | D9: Video | E9: 2025-06-07 | F9: 1436 | G9: 9281 | H9: 1238 | I9: 6149 | J9: 23847 | K9: 334.8 | L9: =F9+G9+H9+I9 -> 18104 | M9: =J9-L9 -> 5743 | N9: =ROUND((J9-L9)/L9*100,2) -> 31.72
A10: 9 | B10: Short_Asset_079 | C10: Short Reel | D10: Video | E10: 2025-02-17 | F10: 579 | G10: 1830 | H10: 671 | I10: 899 | J10: 11514 | K10: 44.8 | L10: =F10+G10+H10+I10 -> 3979 | M10: =J10-L10 -> 7535 | N10: =ROUND((J10-L10)/L10*100,2) -> 189.37
A11: 10 | B11: Product_Asset_066 | C11: Product Photo | D11: Photography | E11: 2025-12-07 | F11: 996 | G11: 1051 | H11: 298 | I11: 822 | J11: 8819 | K11: 26.9 | L11: =F11+G11+H11+I11 -> 3167 | M11: =J11-L11 -> 5652 | N11: =ROUND((J11-L11)/L11*100,2) -> 178.47
A12: 11 | B12: Infographic_Asset_112 | C12: Infographic | D12: Graphic | E12: 2025-10-03 | F12: 1 | G12: 577 | H12: 258 | I12: 209 | J12: 2995 | K12: 14.8 | L12: =F12+G12+H12+I12 -> 1045 | M12: =J12-L12 -> 1950 | N12: =ROUND((J12-L12)/L12*100,2) -> 186.6
A13: 12 | B13: Infographic_Asset_115 | C13: Infographic | D13: Graphic | E13: 2025-05-15 | F13: 87 | G13: 1435 | H13: 242 | I13: 324 | J13: 4793 | K13: 45.8 | L13: =F13+G13+H13+I13 -> 2088 | M13: =J13-L13 -> 2705 | N13: =ROUND((J13-L13)/L13*100,2) -> 129.55
... A121: 120 | B121: Cinematic_Asset_043 | C121: Cinematic Animation Video | D121: Video | E121: 2025-10-12 | F121: 1393 | G121: 15954 | H121: 884 | I121: 8556 | J121: 60174 | K121: 511.7 | L121: =F121+G121+H121+I121 -> 26787 | M121: =J121-L121 -> 33387 | N121: =ROUND((J121-L121)/L121*100,2) -> 124.64

Sheet ROI_Summary
A1: Media Type | B1: Assets | C1: Avg Equipment | D1: Avg Labor | E1: Avg Software | F1: Avg Post-Production | G1: Total Cost | H1: Total Revenue | I1: Total Profit | J1: ROI %
A2: DSLR Portrait | B2: =COUNTIF(Asset_Data!$C$2:$C$121,A2) -> 24 | C2: =AVERAGEIF(Asset_Data!$C$2:$C$121,A2,Asset_Data!$F$2:$F$121) -> 1587.3333 | D2: =AVERAGEIF(Asset_Data!$C$2:$C$121,A2,Asset_Data!$G$2:$G$121) -> 2535.375 | E2: =AVERAGEIF(Asset_Data!$C$2:$C$121,A2,Asset_Data!$H$2:$H$121) -> 242.125 | F2: =AVERAGEIF(Asset_Data!$C$2:$C$121,A2,Asset_Data!$I$2:$I$121) -> 848.875 | G2: =SUMIF(Asset_Data!$C$2:$C$121,A2,Asset_Data!$L$2:$L$121) -> 125129 | H2: =SUMIF(Asset_Data!$C$2:$C$121,A2,Asset_Data!$J$2:$J$121) -> 303355 | I2: =H2-G2 -> 178226 | J2: =ROUND(I2/G2*100,2) -> 142.43
A3: Cinematic Animation Video | B3: =COUNTIF(Asset_Data!$C$2:$C$121,A3) -> 24 | C3: =AVERAGEIF(Asset_Data!$C$2:$C$121,A3,Asset_Data!$F$2:$F$121) -> 1105.0417 | D3: =AVERAGEIF(Asset_Data!$C$2:$C$121,A3,Asset_Data!$G$2:$G$121) -> 12596.167 | E3: =AVERAGEIF(Asset_Data!$C$2:$C$121,A3,Asset_Data!$H$2:$H$121) -> 1507.1667 | F3: =AVERAGEIF(Asset_Data!$C$2:$C$121,A3,Asset_Data!$I$2:$I$121) -> 5337.0833 | G3: =SUMIF(Asset_Data!$C$2:$C$121,A3,Asset_Data!$L$2:$L$121) -> 493091 | H3: =SUMIF(Asset_Data!$C$2:$C$121,A3,Asset_Data!$J$2:$J$121) -> 900893 | I3: =H3-G3 -> 407802 | J3: =ROUND(I3/G3*100,2) -> 82.7
A4: Product Photo | B4: =COUNTIF(Asset_Data!$C$2:$C$121,A4) -> 24 | C4: =AVERAGEIF(Asset_Data!$C$2:$C$121,A4,Asset_Data!$F$2:$F$121) -> 777 | D4: =AVERAGEIF(Asset_Data!$C$2:$C$121,A4,Asset_Data!$G$2:$G$121) -> 1471.9167 | E4: =AVERAGEIF(Asset_Data!$C$2:$C$121,A4,Asset_Data!$H$2:$H$121) -> 203.04167 | F4: =AVERAGEIF(Asset_Data!$C$2:$C$121,A4,Asset_Data!$I$2:$I$121) -> 587.375 | G4: =SUMIF(Asset_Data!$C$2:$C$121,A4,Asset_Data!$L$2:$L$121) -> 72944 | H4: =SUMIF(Asset_Data!$C$2:$C$121,A4,Asset_Data!$J$2:$J$121) -> 179367 | I4: =H4-G4 -> 106423 | J4: =ROUND(I4/G4*100,2) -> 145.9
A5: Short Reel | B5: =COUNTIF(Asset_Data!$C$2:$C$121,A5) -> 24 | C5: =AVERAGEIF(Asset_Data!$C$2:$C$121,A5,Asset_Data!$F$2:$F$121) -> 526.29167 | D5: =AVERAGEIF(Asset_Data!$C$2:$C$121,A5,Asset_Data!$G$2:$G$121) -> 2008.4583 | E5: =AVERAGEIF(Asset_Data!$C$2:$C$121,A5,Asset_Data!$H$2:$H$121) -> 464.29167 | F5: =AVERAGEIF(Asset_Data!$C$2:$C$121,A5,Asset_Data!$I$2:$I$121) -> 1152.1667 | G5: =SUMIF(Asset_Data!$C$2:$C$121,A5,Asset_Data!$L$2:$L$121) -> 99629 | H5: =SUMIF(Asset_Data!$C$2:$C$121,A5,Asset_Data!$J$2:$J$121) -> 260723 | I5: =H5-G5 -> 161094 | J5: =ROUND(I5/G5*100,2) -> 161.69
A6: Infographic | B6: =COUNTIF(Asset_Data!$C$2:$C$121,A6) -> 24 | C6: =AVERAGEIF(Asset_Data!$C$2:$C$121,A6,Asset_Data!$F$2:$F$121) -> 49.416667 | D6: =AVERAGEIF(Asset_Data!$C$2:$C$121,A6,Asset_Data!$G$2:$G$121) -> 1041.0417 | E6: =AVERAGEIF(Asset_Data!$C$2:$C$121,A6,Asset_Data!$H$2:$H$121) -> 276.70833 | F6: =AVERAGEIF(Asset_Data!$C$2:$C$121,A6,Asset_Data!$I$2:$I$121) -> 266.04167 | G6: =SUMIF(Asset_Data!$C$2:$C$121,A6,Asset_Data!$L$2:$L$121) -> 39197 | H6: =SUMIF(Asset_Data!$C$2:$C$121,A6,Asset_Data!$J$2:$J$121) -> 89334 | I6: =H6-G6 -> 50137 | J6: =ROUND(I6/G6*100,2) -> 127.91
A7: TOTAL | B7: =SUM(B2:B6) -> 120 | G7: =SUM(G2:G6) -> 829990 | H7: =SUM(H2:H6) -> 1733672 | I7: =H7-G7 -> 903682 | J7: =ROUND(I7/G7*100,2) -> 108.88
A9: Best ROI format: | B9: =INDEX(A2:A6,MATCH(MAX(J2:J6),J2:J6,0)) -> Short Reel
A10: Highest-cost format: | B10: =INDEX(A2:A6,MATCH(MAX(G2:G6),G2:G6,0)) -> Cinematic Animation Video
